README.md
setup.py
freekassa_api/__init__.py
freekassa_api/api.py
freekassa_api/api_base.py
freekassa_api/constants.py
freekassa_api/helpers.py
freekassa_api/models.py
freekassa_api.egg-info/PKG-INFO
freekassa_api.egg-info/SOURCES.txt
freekassa_api.egg-info/dependency_links.txt
freekassa_api.egg-info/requires.txt
freekassa_api.egg-info/top_level.txt