Metadata-Version: 2.1
Name: freekassa-api
Version: 0.0.3
Summary: Freekassa API
Home-page: https://github.com/LDmitriy7/freekassa_api.git
Author: LDmitriy7
Author-email: ldm.work2019@gmail.com
License: MIT
Platform: UNKNOWN
